plugorm/__init__.py
plugorm/_version.py
plugorm/core.py
plugorm/drivers.py
plugorm/errors.py
plugorm/toolchain.py
plugorm/utils.py
plugorm-0.2.0.dist-info/licenses/LICENSE.txt
plugorm-0.2.0.dist-info/METADATA
plugorm-0.2.0.dist-info/WHEEL
plugorm-0.2.0.dist-info/top_level.txt
plugorm-0.2.0.dist-info/RECORD
